simplemodulebylukasabcde/__init__.py
simplemodulebylukasabcde/add.py
simplemodulebylukasabcde/sub/__init__.py
simplemodulebylukasabcde/sub/subtract.py
simplemodulebylukasabcde-0.0.1.dist-info/METADATA
simplemodulebylukasabcde-0.0.1.dist-info/WHEEL
simplemodulebylukasabcde-0.0.1.dist-info/top_level.txt
simplemodulebylukasabcde-0.0.1.dist-info/RECORD
